hc_simplecalc/__init__.py
hc_simplecalc/calc.py
hc_simpleCalc-0.5.0.dist-info/METADATA
hc_simpleCalc-0.5.0.dist-info/WHEEL
hc_simpleCalc-0.5.0.dist-info/top_level.txt
hc_simpleCalc-0.5.0.dist-info/RECORD
