Metadata-Version: 2.1
Name: hc_simpleCalc
Version: 0.5.0
Summary: Default template for PDM package
Author-email: NishNovae <raecrowned@gmail.com>
License: MIT
Requires-Python: >=3.9
